contracts/Context.sol
contracts/Escrow.sol
contracts/EscrowFactory.sol
contracts/HMToken.sol
contracts/HMTokenInterface.sol
contracts/Migrations.sol
contracts/Ownable.sol
contracts/SafeMath.sol
hmt_escrow/__init__.py
hmt_escrow/eth_bridge.py
hmt_escrow/job.py
hmt_escrow/kvstore_abi.py
hmt_escrow/storage.py
hmt_escrow/utils.py
hmt_escrow/crypto/__init__.py
hmt_escrow/crypto/encryption.py
hmt_escrow/crypto/exceptions.py
migrations/1_initial_migration.js
migrations/2_deploy_contracts.js
test/__init__.py
test/hmt_escrow/__init__.py
test/hmt_escrow/test_eth_bridge.py
test/hmt_escrow/test_job.py
test/hmt_escrow/test_utils.py
test/hmt_escrow/crypto/__init__.py
test/hmt_escrow/crypto/test_crypto.py
test/hmt_escrow/crypto/test_encryption.py
test/hmt_escrow/storage/__init__.py
test/hmt_escrow/storage/test_bucket.py
test/hmt_escrow/storage/test_storage.py
test/hmt_escrow/utils/__init__.py
test/hmt_escrow/utils/job.py
test/hmt_escrow/utils/manifest.py
hmt_escrow-0.14.6.dist-info/LICENSE
hmt_escrow-0.14.6.dist-info/METADATA
hmt_escrow-0.14.6.dist-info/WHEEL
hmt_escrow-0.14.6.dist-info/top_level.txt
hmt_escrow-0.14.6.dist-info/zip-safe
hmt_escrow-0.14.6.dist-info/RECORD
