Metadata-Version: 2.1
Name: hmt-escrow
Version: 0.14.6
Summary: A python library to launch escrow contracts to the HUMAN network.
Home-page: https://github.com/humanprotocol/hmt-escrow
Author: HUMAN Protocol
Classifier: Intended Audience :: Developers
Classifier: Operating System :: OS Independent
Classifier: Programming Language :: Python
License-File: LICENSE
Requires-Dist: boto3
Requires-Dist: cryptography
Requires-Dist: hmt-basemodels (>=0.1.18)
Requires-Dist: web3 (==5.24.0)
